{
    "links": [], 
    "nodes": [
        {
            "compartment": "metaid_0000072", 
            "id": "metaid_0000119", 
            "species_name": "Q_sto2"
        }, 
        {
            "compartment": "metaid_0000072", 
            "id": "metaid_0000104", 
            "species_name": "I_l"
        }, 
        {
            "compartment": "metaid_0000072", 
            "id": "metaid_0000108", 
            "species_name": "Q_gut"
        }, 
        {
            "compartment": "metaid_0000072", 
            "id": "metaid_0000111", 
            "species_name": "X"
        }, 
        {
            "compartment": "metaid_0000072", 
            "id": "metaid_0000105", 
            "species_name": "I_p"
        }, 
        {
            "compartment": "metaid_0000072", 
            "id": "metaid_0000109", 
            "species_name": "I_1"
        }, 
        {
            "compartment": "metaid_0000072", 
            "id": "metaid_0000110", 
            "species_name": "I_d"
        }, 
        {
            "compartment": "metaid_0000072", 
            "id": "metaid_0000102", 
            "species_name": "G_p"
        }, 
        {
            "compartment": "metaid_0000072", 
            "id": "metaid_0000106", 
            "species_name": "Q_sto1"
        }, 
        {
            "compartment": "metaid_0000072", 
            "id": "metaid_0000113", 
            "species_name": "Y"
        }, 
        {
            "compartment": "metaid_0000072", 
            "id": "metaid_0000103", 
            "species_name": "G_t"
        }, 
        {
            "compartment": "metaid_0000072", 
            "id": "metaid_0000112", 
            "species_name": "I_po"
        }
    ]
}